flamingText/__init__.py
flamingText/constants.py
flamingText/main.py
FlamingText-0.0.7.dist-info/METADATA
FlamingText-0.0.7.dist-info/WHEEL
FlamingText-0.0.7.dist-info/top_level.txt
FlamingText-0.0.7.dist-info/RECORD
